pytest_workflow/__init__.py
pytest_workflow/content_tests.py
pytest_workflow/file_tests.py
pytest_workflow/plugin.py
pytest_workflow/schema.py
pytest_workflow/util.py
pytest_workflow/workflow.py
pytest_workflow/schema/schema.json
pytest_workflow-2.1.0.dist-info/LICENSE
pytest_workflow-2.1.0.dist-info/METADATA
pytest_workflow-2.1.0.dist-info/WHEEL
pytest_workflow-2.1.0.dist-info/entry_points.txt
pytest_workflow-2.1.0.dist-info/top_level.txt
pytest_workflow-2.1.0.dist-info/RECORD
