Metadata-Version: 2.1
Name: pytest-workflow
Version: 2.1.0
Summary: A pytest plugin for configuring workflow/pipeline tests using YAML files
Home-page: https://github.com/LUMC/pytest-workflow
Author: Leiden University Medical Center
Author-email: sasc@lumc.nl
License: AGPL-3.0-or-later
Keywords: pytest workflow pipeline yaml yml wdl cromwell snakemake
Classifier: Programming Language :: Python :: 3 :: Only
Classifier: Programming Language :: Python :: 3
Classifier: Programming Language :: Python :: 3.8
Classifier: Programming Language :: Python :: 3.9
Classifier: Programming Language :: Python :: 3.10
Classifier: Programming Language :: Python :: 3.11
Classifier: Programming Language :: Python :: 3.12
Classifier: Development Status :: 5 - Production/Stable
Classifier: License :: OSI Approved :: GNU Affero General Public License v3 or later (AGPLv3+)
Classifier: Framework :: Pytest
Requires-Python: >=3.8
License-File: LICENSE
Requires-Dist: pytest >=7.0.0
Requires-Dist: pyyaml
Requires-Dist: jsonschema
Requires-Dist: xopen >=1.4.0
Requires-Dist: zstandard
